{"stats":{"minecraft:dropped":{"minecraft:enchanted_book":2,"minecraft:bamboo_trapdoor":1,"minecraft:flint":14,"minecraft:snowball":284,"minecraft:cherry_leaves":1,"minecraft:iron_pickaxe":1,"minecraft:music_disc_cat":1,"minecraft:gravel":64,"minecraft:rotten_flesh":2,"minecraft:flint_and_steel":1,"minecraft:carrot":1,"minecraft:deepslate_bricks":1,"minecraft:diamond_pickaxe":1,"minecraft:hopper":4,"minecraft:yellow_bed":1,"minecraft:oak_boat":1,"minecraft:spider_eye":1,"minecraft:cracked_deepslate_bricks":1,"minecraft:egg":3},"minecraft:broken":{"minecraft:iron_shovel":4,"minecraft:iron_pickaxe":13,"minecraft:golden_pickaxe":1,"minecraft:iron_hoe":1},"minecraft:used":{"minecraft:cherry_sapling":8,"minecraft:iron_shovel":1141,"minecraft:flint_and_steel":2,"minecraft:chiseled_tuff":2,"minecraft:ladder":16,"minecraft:diamond_hoe":3578,"minecraft:chest":11,"minecraft:iron_sword":97,"minecraft:bamboo_door":10,"minecraft:torch":443,"minecraft:soul_sand":2,"minecraft:dirt":270,"minecraft:anvil":1,"minecraft:hopper":5,"minecraft:cherry_pressure_plate":3,"minecraft:carrot":78,"minecraft:tuff":23,"minecraft:obsidian":13,"minecraft:iron_hoe":251,"minecraft:iron_axe":237,"minecraft:cherry_slab":8,"minecraft:cherry_trapdoor":45,"minecraft:cherry_fence_gate":3,"minecraft:bamboo":4,"minecraft:redstone_lamp":3,"minecraft:hay_block":26,"minecraft:furnace":1,"minecraft:skeleton_skull":4,"minecraft:cooked_beef":4,"minecraft:cobbled_deepslate":20,"minecraft:cherry_fence":90,"minecraft:iron_leggings":1,"minecraft:dark_oak_sapling":4,"minecraft:wheat_seeds":49,"minecraft:bamboo_trapdoor":12,"minecraft:water_bucket":18,"minecraft:cobblestone_stairs":219,"minecraft:snow_block":16,"minecraft:glass_bottle":1,"minecraft:oak_planks":14,"minecraft:leather_chestplate":1,"minecraft:cherry_planks":39,"minecraft:redstone_block":3,"minecraft:leather_boots":1,"minecraft:golden_apple":1,"minecraft:crafting_table":5,"minecraft:pumpkin_seeds":16,"minecraft:shears":87,"minecraft:diamond_pickaxe":448,"minecraft:melon_slice":5,"minecraft:bread":24,"minecraft:iron_pickaxe":3278,"minecraft:leather_helmet":1,"minecraft:gravel":80,"minecraft:tuff_brick_slab":10,"minecraft:potion":1,"minecraft:cherry_stairs":47,"minecraft:cobblestone":100,"minecraft:bone_meal":130,"minecraft:glass_pane":12,"minecraft:bucket":21,"minecraft:kelp":211,"minecraft:yellow_bed":6,"minecraft:tropical_fish_bucket":2,"minecraft:oak_boat":3,"minecraft:experience_bottle":16,"minecraft:golden_pickaxe":32,"minecraft:gray_wool":68,"minecraft:soul_torch":34},"minecraft:picked_up":{"minecraft:tuff_brick_slab":10,"minecraft:crafting_table":1,"minecraft:wheat":9,"minecraft:redstone_block":2,"minecraft:ladder":1,"minecraft:redstone_lamp":3,"minecraft:potion":1,"minecraft:stripped_cherry_log":1,"minecraft:amethyst_block":6,"minecraft:string":5,"minecraft:raw_copper":52,"minecraft:flint_and_steel":1,"minecraft:cherry_pressure_plate":3,"minecraft:sticky_piston":5,"minecraft:glass_pane":14,"minecraft:cobbled_deepslate":1599,"minecraft:bucket":3,"minecraft:white_tulip":4,"minecraft:oak_boat":4,"minecraft:chiseled_tuff":2,"minecraft:calcite":4,"minecraft:poppy":64,"minecraft:iron_pickaxe":2,"minecraft:melon_slice":5,"minecraft:chest":1,"minecraft:diamond_hoe":2,"minecraft:cherry_trapdoor":3,"minecraft:egg":6,"minecraft:stick":29,"minecraft:raw_iron":5,"minecraft:cherry_stairs":7,"minecraft:torch":111,"minecraft:target":1,"minecraft:cherry_log":142,"minecraft:bamboo_door":7,"minecraft:diorite":56,"minecraft:carrot":54,"minecraft:redstone":79,"minecraft:cherry_fence_gate":1,"minecraft:rotten_flesh":2,"minecraft:shears":1,"minecraft:deepslate_bricks":1,"minecraft:hay_block":85,"minecraft:iron_block":151,"minecraft:cracked_deepslate_bricks":1,"minecraft:pink_tulip":10,"minecraft:obsidian":1,"minecraft:mutton":2,"minecraft:cobblestone":1189,"minecraft:snowball":634,"minecraft:skeleton_skull":4,"minecraft:white_wool":1,"minecraft:pink_petals":162,"minecraft:cooked_beef":124,"minecraft:cherry_planks":17,"minecraft:cherry_leaves":1,"minecraft:water_bucket":3,"minecraft:andesite":82,"minecraft:flint":30,"minecraft:tuff":246,"minecraft:oak_log":12,"minecraft:cherry_fence":11,"minecraft:yellow_bed":7,"minecraft:cobblestone_stairs":13,"minecraft:dirt":474,"minecraft:kelp":850,"minecraft:wheat_seeds":57,"minecraft:orange_tulip":8,"minecraft:raw_gold":4,"minecraft:iron_ingot":8,"minecraft:cherry_sign":1,"minecraft:bamboo":273,"minecraft:oak_planks":4,"minecraft:soul_sand":3,"minecraft:pumpkin":4,"minecraft:gravel":366,"minecraft:soul_torch":4,"minecraft:spider_eye":1,"minecraft:bamboo_trapdoor":1,"minecraft:diamond":24,"minecraft:bone_meal":234,"minecraft:granite":19,"minecraft:cherry_sapling":55,"minecraft:gray_wool":156,"minecraft:bread":29,"minecraft:emerald":1,"minecraft:diamond_pickaxe":1,"minecraft:sunflower":11,"minecraft:coal":222,"minecraft:hopper":3},"minecraft:crafted":{"minecraft:cherry_planks":568,"minecraft:oak_planks":48,"minecraft:cherry_pressure_plate":3,"minecraft:cherry_slab":12,"minecraft:furnace":1,"minecraft:cobblestone_stairs":252,"minecraft:bamboo_door":3,"minecraft:flint_and_steel":1,"minecraft:bamboo_block":21,"minecraft:cherry_trapdoor":46,"minecraft:hopper":3,"minecraft:diamond_helmet":1,"minecraft:diamond_leggings":1,"minecraft:iron_axe":2,"minecraft:ladder":15,"minecraft:iron_hoe":1,"minecraft:cherry_stairs":52,"minecraft:chest":13,"minecraft:redstone_block":2,"minecraft:cherry_fence":87,"minecraft:cherry_fence_gate":3,"minecraft:wheat":180,"minecraft:crafting_table":4,"minecraft:iron_sword":1,"minecraft:bucket":2,"minecraft:pumpkin_seeds":16,"minecraft:air":0,"minecraft:bread":49,"minecraft:oak_boat":1,"minecraft:bamboo_planks":42,"minecraft:diamond_pickaxe":1,"minecraft:stick":216,"minecraft:iron_ingot":13,"minecraft:iron_pickaxe":14,"minecraft:iron_block":47,"minecraft:snow_block":73,"minecraft:iron_shovel":5,"minecraft:iron_leggings":1,"minecraft:anvil":1,"minecraft:torch":332,"minecraft:bamboo_trapdoor":12,"minecraft:shears":3},"minecraft:mined":{"minecraft:tuff":246,"minecraft:cherry_pressure_plate":3,"minecraft:deepslate_diamond_ore":24,"minecraft:cherry_log":142,"minecraft:cobblestone_stairs":13,"minecraft:sculk_vein":311,"minecraft:cherry_sapling":1,"minecraft:stripped_cherry_log":1,"minecraft:bamboo_door":4,"minecraft:obsidian":1,"minecraft:ladder":1,"minecraft:cherry_trapdoor":3,"minecraft:granite":19,"minecraft:budding_amethyst":1,"minecraft:grass_block":388,"minecraft:deepslate_bricks":2,"minecraft:kelp":4,"minecraft:hopper":3,"minecraft:hay_block":87,"minecraft:redstone_ore":2,"minecraft:sculk_catalyst":13,"minecraft:carrots":15,"minecraft:fire":1,"minecraft:iron_ore":4,"minecraft:sticky_piston":5,"minecraft:cobbled_deepslate":2,"minecraft:snow":27,"minecraft:andesite":82,"minecraft:target":1,"minecraft:pumpkin":4,"minecraft:sculk_shrieker":44,"minecraft:skeleton_wall_skull":1,"minecraft:deepslate_iron_ore":1,"minecraft:packed_ice":62,"minecraft:pink_tulip":10,"minecraft:bamboo":39,"minecraft:white_tulip":4,"minecraft:stone":1179,"minecraft:cherry_fence_gate":1,"minecraft:cherry_stairs":7,"minecraft:deepslate_redstone_ore":16,"minecraft:soul_wall_torch":1,"minecraft:redstone_block":2,"minecraft:cherry_planks":16,"minecraft:soul_sand":3,"minecraft:kelp_plant":13,"minecraft:snow_block":291,"minecraft:soul_fire":2,"minecraft:soul_torch":3,"minecraft:powder_snow":5,"minecraft:crafting_table":1,"minecraft:torch":62,"minecraft:short_grass":256,"minecraft:emerald_ore":1,"minecraft:calcite":4,"minecraft:melon":1,"minecraft:chest":1,"minecraft:sculk_sensor":96,"minecraft:copper_ore":9,"minecraft:tall_grass":22,"minecraft:cobblestone":20,"minecraft:deepslate_gold_ore":4,"minecraft:oak_planks":4,"minecraft:cracked_deepslate_bricks":1,"minecraft:sculk":3220,"minecraft:diorite":56,"minecraft:wall_torch":34,"minecraft:amethyst_block":9,"minecraft:deepslate_copper_ore":5,"minecraft:skeleton_skull":3,"minecraft:pink_petals":31,"minecraft:cherry_fence":11,"minecraft:gray_wool":99,"minecraft:bamboo_trapdoor":1,"minecraft:wheat":10,"minecraft:ice":11,"minecraft:orange_tulip":8,"minecraft:yellow_bed":6,"minecraft:oak_log":12,"minecraft:coal_ore":224,"minecraft:cherry_leaves":26,"minecraft:sunflower":11,"minecraft:gravel":302,"minecraft:dirt":76,"minecraft:smooth_basalt":3,"minecraft:oak_leaves":2,"minecraft:deepslate":1610,"minecraft:redstone_lamp":3},"minecraft:custom":{"minecraft:interact_with_smithing_table":1,"minecraft:interact_with_anvil":3,"minecraft:mob_kills":18,"minecraft:animals_bred":3,"minecraft:inspect_hopper":1,"minecraft:interact_with_crafting_table":71,"minecraft:leave_game":20,"minecraft:time_since_death":9392,"minecraft:climb_one_cm":22197,"minecraft:sprint_one_cm":1396493,"minecraft:walk_one_cm":1389078,"minecraft:drop":42,"minecraft:talked_to_villager":2,"minecraft:play_time":614054,"minecraft:deaths":3,"minecraft:sneak_time":181438,"minecraft:walk_under_water_one_cm":230854,"minecraft:boat_one_cm":170657,"minecraft:jump":3602,"minecraft:walk_on_water_one_cm":62146,"minecraft:total_world_time":614054,"minecraft:interact_with_furnace":8,"minecraft:sleep_in_bed":16,"minecraft:time_since_rest":9426,"minecraft:damage_taken":2299,"minecraft:damage_dealt":3079,"minecraft:swim_one_cm":109706,"minecraft:fly_one_cm":159726,"minecraft:open_chest":170,"minecraft:crouch_one_cm":741467,"minecraft:interact_with_smoker":2,"minecraft:fall_one_cm":84822},"minecraft:killed":{"minecraft:spider":5,"minecraft:skeleton":1,"minecraft:drowned":1,"minecraft:sheep":1,"minecraft:zombie":10}},"DataVersion":3955}